sin_miss/__init__.py
sin_miss/miss_val.py
101703549_missing_val-0.0.1.dist-info/LICENSE
101703549_missing_val-0.0.1.dist-info/METADATA
101703549_missing_val-0.0.1.dist-info/WHEEL
101703549_missing_val-0.0.1.dist-info/entry_points.txt
101703549_missing_val-0.0.1.dist-info/top_level.txt
101703549_missing_val-0.0.1.dist-info/RECORD
