Metadata-Version: 2.1
Name: 101703549-missing-val
Version: 0.0.1
Summary: a package to deal with missing values
Home-page: https://github.com/pypa/missing_values
Author: Simranpreet kaur
Author-email: skaur_be17@thapar.edu
License: UNKNOWN
Platform: UNKNOWN
Classifier: Programming Language :: Python :: 3
Classifier: License :: OSI Approved :: MIT License
Classifier: Operating System :: OS Independent
Requires-Python: >=3.6
Requires-Dist: requests
